LICENSE.txt
MANIFEST.in
README.rst
setup.py
cmsplugin_news/__init__.py
cmsplugin_news/admin.py
cmsplugin_news/cms_app.py
cmsplugin_news/cms_plugins.py
cmsplugin_news/feeds.py
cmsplugin_news/forms.py
cmsplugin_news/menu.py
cmsplugin_news/models.py
cmsplugin_news/navigation.py
cmsplugin_news/settings.py
cmsplugin_news/tests.py
cmsplugin_news/urls.py
cmsplugin_news/views.py
cmsplugin_news.egg-info/PKG-INFO
cmsplugin_news.egg-info/SOURCES.txt
cmsplugin_news.egg-info/dependency_links.txt
cmsplugin_news.egg-info/not-zip-safe
cmsplugin_news.egg-info/requires.txt
cmsplugin_news.egg-info/top_level.txt
cmsplugin_news/locale/de/LC_MESSAGES/django.mo
cmsplugin_news/locale/de/LC_MESSAGES/django.po
cmsplugin_news/locale/es/LC_MESSAGES/django.mo
cmsplugin_news/locale/es/LC_MESSAGES/django.po
cmsplugin_news/locale/eu/LC_MESSAGES/django.mo
cmsplugin_news/locale/eu/LC_MESSAGES/django.po
cmsplugin_news/locale/ru/LC_MESSAGES/django.mo
cmsplugin_news/locale/ru/LC_MESSAGES/django.po
cmsplugin_news/migrations/0001_initial.py
cmsplugin_news/migrations/0002_directlinks.py
cmsplugin_news/migrations/__init__.py
cmsplugin_news/templates/cmsplugin_news/latest_news.html
cmsplugin_news/templates/cmsplugin_news/news_archive.html
cmsplugin_news/templates/cmsplugin_news/news_archive_day.html
cmsplugin_news/templates/cmsplugin_news/news_archive_month.html
cmsplugin_news/templates/cmsplugin_news/news_archive_year.html
cmsplugin_news/templates/cmsplugin_news/news_detail.html
cmsplugin_news/templates/cmsplugin_news/feeds/item_description.html
cmsplugin_news/templates/cmsplugin_news/feeds/item_title.html
cmsplugin_news/templates/cmsplugin_news/widgets/tinymce.html
cmsplugin_news/templates/cmsplugin_news/widgets/wymeditor.html
cmsplugin_news/widgets/__init__.py
cmsplugin_news/widgets/tinymce_widget.py
cmsplugin_news/widgets/wymeditor_widget.py