Metadata-Version: 1.1
Name: cmsplugin-news
Version: 0.4.4
Summary: Simple news plugin for django-cms 2.x
Home-page: http://bitbucket.org/zerok/cmsplugin-news/
Author: Horst Gutmann
Author-email: zerok@zerokspot.com
License: BSD
Platform: UNKNOWN
Classifier: Development Status :: 4 - Beta
Classifier: Environment :: Web Environment
Classifier: Intended Audience :: Developers
Classifier: License :: OSI Approved :: BSD License
Classifier: Operating System :: OS Independent
Classifier: Programming Language :: Python
Classifier: Framework :: Django
